LICENSE
README.md
pyproject.toml
setup.py
datahub_py/__init__.py
datahub_py.egg-info/PKG-INFO
datahub_py.egg-info/SOURCES.txt
datahub_py.egg-info/dependency_links.txt
datahub_py.egg-info/requires.txt
datahub_py.egg-info/top_level.txt
datahub_py/Beacon/Network.py
datahub_py/Beacon/__init__.py
datahub_py/CTRL/__init__.py
datahub_py/Project/__init__.py