Metadata-Version: 2.1
Name: datahub-py
Version: 0.0.15
Summary: Datahub core
Home-page: https://github.com/26medias/Datahub-py
Author: Julien L
Author-email: Julien L <julien@leap-forward.ca>
Project-URL: Homepage, https://github.com/26medias/Datahub-py
Project-URL: Bug Tracker, https://github.com/26medias/Datahub-py/issues
Classifier: Programming Language :: Python :: 3
Classifier: License :: OSI Approved :: MIT License
Classifier: Operating System :: OS Independent
Requires-Python: >=3.8
License-File: LICENSE
